lib/__init__.py
lib/ns3.py
cnsns3-0.0.1.dist-info/METADATA
cnsns3-0.0.1.dist-info/WHEEL
cnsns3-0.0.1.dist-info/top_level.txt
cnsns3-0.0.1.dist-info/RECORD
