Metadata-Version: 2.1
Name: cnsns3
Version: 0.0.1
Summary: None of your business
Home-page: UNKNOWN
Author: Anonymous
Author-email: <ghanta@bich.com>
License: UNKNOWN
Keywords: python,ns3
Platform: UNKNOWN
Classifier: Development Status :: 1 - Planning
Classifier: Intended Audience :: Developers
Classifier: Programming Language :: Python :: 3
Classifier: Operating System :: OS Independent
